{
	"start":	{
		"connected":	[{
				"socket":	5,
				"local_host":	"192.168.0.140",
				"local_port":	5201,
				"remote_host":	"192.168.0.126",
				"remote_port":	38673
			}],
		"version":	"iperf 3.16",
		"system_info":	"Linux nixos 6.1.79 #1-NixOS SMP PREEMPT_DYNAMIC Fri Feb 23 08:12:53 UTC 2024 x86_64",
		"target_bitrate":	80000000,
		"timestamp":	{
			"time":	"Sat, 20 Apr 2024 03:57:44 GMT",
			"timesecs":	1713585464
		},
		"accepted_connection":	{
			"host":	"192.168.0.126",
			"port":	36688
		},
		"cookie":	"qifed5nzwh3pyi2mstvtjlhvhskvs7ysarie",
		"target_bitrate":	80000000,
		"fq_rate":	0,
		"sock_bufsize":	0,
		"sndbuf_actual":	212992,
		"rcvbuf_actual":	212992,
		"test_start":	{
			"protocol":	"UDP",
			"num_streams":	1,
			"blksize":	1280,
			"omit":	0,
			"duration":	30,
			"bytes":	0,
			"blocks":	0,
			"reverse":	0,
			"tos":	0,
			"target_bitrate":	80000000,
			"bidir":	0,
			"fqrate":	0
		}
	},
	"intervals":	[{
			"streams":	[{
					"socket":	5,
					"start":	0,
					"end":	1.000059,
					"seconds":	1.0000590085983276,
					"bytes":	9982720,
					"bits_per_second":	79857047.747545838,
					"jitter_ms":	0.15101403154385218,
					"lost_packets":	0,
					"packets":	7799,
					"lost_percent":	0,
					"omitted":	false,
					"sender":	false
				}],
			"sum":	{
				"start":	0,
				"end":	1.000059,
				"seconds":	1.0000590085983276,
				"bytes":	9982720,
				"bits_per_second":	79857047.747545838,
				"jitter_ms":	0.15101403154385218,
				"lost_packets":	0,
				"packets":	7799,
				"lost_percent":	0,
				"omitted":	false,
				"sender":	false
			}
		}, {
			"streams":	[{
					"socket":	5,
					"start":	1.000059,
					"end":	2.000068,
					"seconds":	1.0000089406967163,
					"bytes":	10000640,
					"bits_per_second":	80004404.704881564,
					"jitter_ms":	0.19790508536699361,
					"lost_packets":	0,
					"packets":	7813,
					"lost_percent":	0,
					"omitted":	false,
					"sender":	false
				}],
			"sum":	{
				"start":	1.000059,
				"end":	2.000068,
				"seconds":	1.0000089406967163,
				"bytes":	10000640,
				"bits_per_second":	80004404.704881564,
				"jitter_ms":	0.19790508536699361,
				"lost_packets":	0,
				"packets":	7813,
				"lost_percent":	0,
				"omitted":	false,
				"sender":	false
			}
		}, {
			"streams":	[{
					"socket":	5,
					"start":	2.000068,
					"end":	3.000074,
					"seconds":	1.0000059604644775,
					"bytes":	9999360,
					"bits_per_second":	79994403.196201354,
					"jitter_ms":	0.17816072072874342,
					"lost_packets":	0,
					"packets":	7812,
					"lost_percent":	0,
					"omitted":	false,
					"sender":	false
				}],
			"sum":	{
				"start":	2.000068,
				"end":	3.000074,
				"seconds":	1.0000059604644775,
				"bytes":	9999360,
				"bits_per_second":	79994403.196201354,
				"jitter_ms":	0.17816072072874342,
				"lost_packets":	0,
				"packets":	7812,
				"lost_percent":	0,
				"omitted":	false,
				"sender":	false
			}
		}, {
			"streams":	[{
					"socket":	5,
					"start":	3.000074,
					"end":	4.000068,
					"seconds":	0.99999397993087769,
					"bytes":	10000640,
					"bits_per_second":	80005601.639252037,
					"jitter_ms":	0.19409634782245649,
					"lost_packets":	0,
					"packets":	7813,
					"lost_percent":	0,
					"omitted":	false,
					"sender":	false
				}],
			"sum":	{
				"start":	3.000074,
				"end":	4.000068,
				"seconds":	0.99999397993087769,
				"bytes":	10000640,
				"bits_per_second":	80005601.639252037,
				"jitter_ms":	0.19409634782245649,
				"lost_packets":	0,
				"packets":	7813,
				"lost_percent":	0,
				"omitted":	false,
				"sender":	false
			}
		}, {
			"streams":	[{
					"socket":	5,
					"start":	4.000068,
					"end":	5.000074,
					"seconds":	1.0000059604644775,
					"bytes":	9999360,
					"bits_per_second":	79994403.196201354,
					"jitter_ms":	0.16895312073713334,
					"lost_packets":	0,
					"packets":	7813,
					"lost_percent":	0,
					"omitted":	false,
					"sender":	false
				}],
			"sum":	{
				"start":	4.000068,
				"end":	5.000074,
				"seconds":	1.0000059604644775,
				"bytes":	9999360,
				"bits_per_second":	79994403.196201354,
				"jitter_ms":	0.16895312073713334,
				"lost_packets":	0,
				"packets":	7813,
				"lost_percent":	0,
				"omitted":	false,
				"sender":	false
			}
		}, {
			"streams":	[{
					"socket":	5,
					"start":	5.000074,
					"end":	6.00005,
					"seconds":	0.99997597932815552,
					"bytes":	9999360,
					"bits_per_second":	79996801.5769193,
					"jitter_ms":	0.19314640628208035,
					"lost_packets":	0,
					"packets":	7812,
					"lost_percent":	0,
					"omitted":	false,
					"sender":	false
				}],
			"sum":	{
				"start":	5.000074,
				"end":	6.00005,
				"seconds":	0.99997597932815552,
				"bytes":	9999360,
				"bits_per_second":	79996801.5769193,
				"jitter_ms":	0.19314640628208035,
				"lost_packets":	0,
				"packets":	7812,
				"lost_percent":	0,
				"omitted":	false,
				"sender":	false
			}
		}, {
			"streams":	[{
					"socket":	5,
					"start":	6.00005,
					"end":	7.00006,
					"seconds":	1.0000100135803223,
					"bytes":	9999360,
					"bits_per_second":	79994078.9728649,
					"jitter_ms":	0.1617750566655935,
					"lost_packets":	0,
					"packets":	7812,
					"lost_percent":	0,
					"omitted":	false,
					"sender":	false
				}],
			"sum":	{
				"start":	6.00005,
				"end":	7.00006,
				"seconds":	1.0000100135803223,
				"bytes":	9999360,
				"bits_per_second":	79994078.9728649,
				"jitter_ms":	0.1617750566655935,
				"lost_packets":	0,
				"packets":	7812,
				"lost_percent":	0,
				"omitted":	false,
				"sender":	false
			}
		}, {
			"streams":	[{
					"socket":	5,
					"start":	7.00006,
					"end":	8.00006,
					"seconds":	1,
					"bytes":	9999360,
					"bits_per_second":	79994880,
					"jitter_ms":	0.15515118780534012,
					"lost_packets":	0,
					"packets":	7812,
					"lost_percent":	0,
					"omitted":	false,
					"sender":	false
				}],
			"sum":	{
				"start":	7.00006,
				"end":	8.00006,
				"seconds":	1,
				"bytes":	9999360,
				"bits_per_second":	79994880,
				"jitter_ms":	0.15515118780534012,
				"lost_packets":	0,
				"packets":	7812,
				"lost_percent":	0,
				"omitted":	false,
				"sender":	false
			}
		}, {
			"streams":	[{
					"socket":	5,
					"start":	8.00006,
					"end":	9.00006,
					"seconds":	1,
					"bytes":	10000640,
					"bits_per_second":	80005120,
					"jitter_ms":	0.16072140626082829,
					"lost_packets":	0,
					"packets":	7813,
					"lost_percent":	0,
					"omitted":	false,
					"sender":	false
				}],
			"sum":	{
				"start":	8.00006,
				"end":	9.00006,
				"seconds":	1,
				"bytes":	10000640,
				"bits_per_second":	80005120,
				"jitter_ms":	0.16072140626082829,
				"lost_packets":	0,
				"packets":	7813,
				"lost_percent":	0,
				"omitted":	false,
				"sender":	false
			}
		}, {
			"streams":	[{
					"socket":	5,
					"start":	9.00006,
					"end":	10.00006,
					"seconds":	1,
					"bytes":	9999360,
					"bits_per_second":	79994880,
					"jitter_ms":	0.16741656916609154,
					"lost_packets":	0,
					"packets":	7812,
					"lost_percent":	0,
					"omitted":	false,
					"sender":	false
				}],
			"sum":	{
				"start":	9.00006,
				"end":	10.00006,
				"seconds":	1,
				"bytes":	9999360,
				"bits_per_second":	79994880,
				"jitter_ms":	0.16741656916609154,
				"lost_packets":	0,
				"packets":	7812,
				"lost_percent":	0,
				"omitted":	false,
				"sender":	false
			}
		}, {
			"streams":	[{
					"socket":	5,
					"start":	10.00006,
					"end":	11.000059,
					"seconds":	0.99999898672103882,
					"bytes":	10000640,
					"bits_per_second":	80005201.067587033,
					"jitter_ms":	0.1606692200774161,
					"lost_packets":	0,
					"packets":	7813,
					"lost_percent":	0,
					"omitted":	false,
					"sender":	false
				}],
			"sum":	{
				"start":	10.00006,
				"end":	11.000059,
				"seconds":	0.99999898672103882,
				"bytes":	10000640,
				"bits_per_second":	80005201.067587033,
				"jitter_ms":	0.1606692200774161,
				"lost_packets":	0,
				"packets":	7813,
				"lost_percent":	0,
				"omitted":	false,
				"sender":	false
			}
		}, {
			"streams":	[{
					"socket":	5,
					"start":	11.000059,
					"end":	12.000078,
					"seconds":	1.0000189542770386,
					"bytes":	9999360,
					"bits_per_second":	79993363.7836216,
					"jitter_ms":	0.15604510438725111,
					"lost_packets":	0,
					"packets":	7812,
					"lost_percent":	0,
					"omitted":	false,
					"sender":	false
				}],
			"sum":	{
				"start":	11.000059,
				"end":	12.000078,
				"seconds":	1.0000189542770386,
				"bytes":	9999360,
				"bits_per_second":	79993363.7836216,
				"jitter_ms":	0.15604510438725111,
				"lost_packets":	0,
				"packets":	7812,
				"lost_percent":	0,
				"omitted":	false,
				"sender":	false
			}
		}, {
			"streams":	[{
					"socket":	5,
					"start":	12.000078,
					"end":	13.000059,
					"seconds":	0.99998098611831665,
					"bytes":	10000640,
					"bits_per_second":	80006641.236810356,
					"jitter_ms":	0.15523111512295235,
					"lost_packets":	0,
					"packets":	7813,
					"lost_percent":	0,
					"omitted":	false,
					"sender":	false
				}],
			"sum":	{
				"start":	12.000078,
				"end":	13.000059,
				"seconds":	0.99998098611831665,
				"bytes":	10000640,
				"bits_per_second":	80006641.236810356,
				"jitter_ms":	0.15523111512295235,
				"lost_packets":	0,
				"packets":	7813,
				"lost_percent":	0,
				"omitted":	false,
				"sender":	false
			}
		}, {
			"streams":	[{
					"socket":	5,
					"start":	13.000059,
					"end":	14.000059,
					"seconds":	1,
					"bytes":	9999360,
					"bits_per_second":	79994880,
					"jitter_ms":	0.15549965715480538,
					"lost_packets":	0,
					"packets":	7812,
					"lost_percent":	0,
					"omitted":	false,
					"sender":	false
				}],
			"sum":	{
				"start":	13.000059,
				"end":	14.000059,
				"seconds":	1,
				"bytes":	9999360,
				"bits_per_second":	79994880,
				"jitter_ms":	0.15549965715480538,
				"lost_packets":	0,
				"packets":	7812,
				"lost_percent":	0,
				"omitted":	false,
				"sender":	false
			}
		}, {
			"streams":	[{
					"socket":	5,
					"start":	14.000059,
					"end":	15.00006,
					"seconds":	1.0000009536743164,
					"bytes":	10000640,
					"bits_per_second":	80005043.701244637,
					"jitter_ms":	0.1562441148554857,
					"lost_packets":	0,
					"packets":	7813,
					"lost_percent":	0,
					"omitted":	false,
					"sender":	false
				}],
			"sum":	{
				"start":	14.000059,
				"end":	15.00006,
				"seconds":	1.0000009536743164,
				"bytes":	10000640,
				"bits_per_second":	80005043.701244637,
				"jitter_ms":	0.1562441148554857,
				"lost_packets":	0,
				"packets":	7813,
				"lost_percent":	0,
				"omitted":	false,
				"sender":	false
			}
		}, {
			"streams":	[{
					"socket":	5,
					"start":	15.00006,
					"end":	16.00006,
					"seconds":	1,
					"bytes":	9999360,
					"bits_per_second":	79994880,
					"jitter_ms":	0.16957930104670949,
					"lost_packets":	0,
					"packets":	7812,
					"lost_percent":	0,
					"omitted":	false,
					"sender":	false
				}],
			"sum":	{
				"start":	15.00006,
				"end":	16.00006,
				"seconds":	1,
				"bytes":	9999360,
				"bits_per_second":	79994880,
				"jitter_ms":	0.16957930104670949,
				"lost_packets":	0,
				"packets":	7812,
				"lost_percent":	0,
				"omitted":	false,
				"sender":	false
			}
		}, {
			"streams":	[{
					"socket":	5,
					"start":	16.00006,
					"end":	17.000059,
					"seconds":	0.99999898672103882,
					"bytes":	10000640,
					"bits_per_second":	80005201.067587033,
					"jitter_ms":	0.161829324668861,
					"lost_packets":	0,
					"packets":	7813,
					"lost_percent":	0,
					"omitted":	false,
					"sender":	false
				}],
			"sum":	{
				"start":	16.00006,
				"end":	17.000059,
				"seconds":	0.99999898672103882,
				"bytes":	10000640,
				"bits_per_second":	80005201.067587033,
				"jitter_ms":	0.161829324668861,
				"lost_packets":	0,
				"packets":	7813,
				"lost_percent":	0,
				"omitted":	false,
				"sender":	false
			}
		}, {
			"streams":	[{
					"socket":	5,
					"start":	17.000059,
					"end":	18.000059,
					"seconds":	1,
					"bytes":	9999360,
					"bits_per_second":	79994880,
					"jitter_ms":	0.16893812367826475,
					"lost_packets":	0,
					"packets":	7812,
					"lost_percent":	0,
					"omitted":	false,
					"sender":	false
				}],
			"sum":	{
				"start":	17.000059,
				"end":	18.000059,
				"seconds":	1,
				"bytes":	9999360,
				"bits_per_second":	79994880,
				"jitter_ms":	0.16893812367826475,
				"lost_packets":	0,
				"packets":	7812,
				"lost_percent":	0,
				"omitted":	false,
				"sender":	false
			}
		}, {
			"streams":	[{
					"socket":	5,
					"start":	18.000059,
					"end":	19.000059,
					"seconds":	1,
					"bytes":	10000640,
					"bits_per_second":	80005120,
					"jitter_ms":	0.16046243986150882,
					"lost_packets":	0,
					"packets":	7813,
					"lost_percent":	0,
					"omitted":	false,
					"sender":	false
				}],
			"sum":	{
				"start":	18.000059,
				"end":	19.000059,
				"seconds":	1,
				"bytes":	10000640,
				"bits_per_second":	80005120,
				"jitter_ms":	0.16046243986150882,
				"lost_packets":	0,
				"packets":	7813,
				"lost_percent":	0,
				"omitted":	false,
				"sender":	false
			}
		}, {
			"streams":	[{
					"socket":	5,
					"start":	19.000059,
					"end":	20.00006,
					"seconds":	1.0000009536743164,
					"bytes":	9999360,
					"bits_per_second":	79994803.711010247,
					"jitter_ms":	0.16824302269206712,
					"lost_packets":	0,
					"packets":	7812,
					"lost_percent":	0,
					"omitted":	false,
					"sender":	false
				}],
			"sum":	{
				"start":	19.000059,
				"end":	20.00006,
				"seconds":	1.0000009536743164,
				"bytes":	9999360,
				"bits_per_second":	79994803.711010247,
				"jitter_ms":	0.16824302269206712,
				"lost_packets":	0,
				"packets":	7812,
				"lost_percent":	0,
				"omitted":	false,
				"sender":	false
			}
		}, {
			"streams":	[{
					"socket":	5,
					"start":	20.00006,
					"end":	21.000059,
					"seconds":	0.99999898672103882,
					"bytes":	10000640,
					"bits_per_second":	80005201.067587033,
					"jitter_ms":	0.15465452516550923,
					"lost_packets":	0,
					"packets":	7813,
					"lost_percent":	0,
					"omitted":	false,
					"sender":	false
				}],
			"sum":	{
				"start":	20.00006,
				"end":	21.000059,
				"seconds":	0.99999898672103882,
				"bytes":	10000640,
				"bits_per_second":	80005201.067587033,
				"jitter_ms":	0.15465452516550923,
				"lost_packets":	0,
				"packets":	7813,
				"lost_percent":	0,
				"omitted":	false,
				"sender":	false
			}
		}, {
			"streams":	[{
					"socket":	5,
					"start":	21.000059,
					"end":	22.000077,
					"seconds":	1.0000180006027222,
					"bytes":	9999360,
					"bits_per_second":	79993440.069864929,
					"jitter_ms":	0.15742436138917895,
					"lost_packets":	0,
					"packets":	7812,
					"lost_percent":	0,
					"omitted":	false,
					"sender":	false
				}],
			"sum":	{
				"start":	21.000059,
				"end":	22.000077,
				"seconds":	1.0000180006027222,
				"bytes":	9999360,
				"bits_per_second":	79993440.069864929,
				"jitter_ms":	0.15742436138917895,
				"lost_packets":	0,
				"packets":	7812,
				"lost_percent":	0,
				"omitted":	false,
				"sender":	false
			}
		}, {
			"streams":	[{
					"socket":	5,
					"start":	22.000077,
					"end":	23.000059,
					"seconds":	0.99998199939727783,
					"bytes":	10000640,
					"bits_per_second":	80006560.166304722,
					"jitter_ms":	0.1612111746959734,
					"lost_packets":	0,
					"packets":	7813,
					"lost_percent":	0,
					"omitted":	false,
					"sender":	false
				}],
			"sum":	{
				"start":	22.000077,
				"end":	23.000059,
				"seconds":	0.99998199939727783,
				"bytes":	10000640,
				"bits_per_second":	80006560.166304722,
				"jitter_ms":	0.1612111746959734,
				"lost_packets":	0,
				"packets":	7813,
				"lost_percent":	0,
				"omitted":	false,
				"sender":	false
			}
		}, {
			"streams":	[{
					"socket":	5,
					"start":	23.000059,
					"end":	24.000059,
					"seconds":	1,
					"bytes":	9999360,
					"bits_per_second":	79994880,
					"jitter_ms":	0.16724455348401107,
					"lost_packets":	0,
					"packets":	7812,
					"lost_percent":	0,
					"omitted":	false,
					"sender":	false
				}],
			"sum":	{
				"start":	23.000059,
				"end":	24.000059,
				"seconds":	1,
				"bytes":	9999360,
				"bits_per_second":	79994880,
				"jitter_ms":	0.16724455348401107,
				"lost_packets":	0,
				"packets":	7812,
				"lost_percent":	0,
				"omitted":	false,
				"sender":	false
			}
		}, {
			"streams":	[{
					"socket":	5,
					"start":	24.000059,
					"end":	25.00006,
					"seconds":	1.0000009536743164,
					"bytes":	10000640,
					"bits_per_second":	80005043.701244637,
					"jitter_ms":	0.16131707461331851,
					"lost_packets":	0,
					"packets":	7813,
					"lost_percent":	0,
					"omitted":	false,
					"sender":	false
				}],
			"sum":	{
				"start":	24.000059,
				"end":	25.00006,
				"seconds":	1.0000009536743164,
				"bytes":	10000640,
				"bits_per_second":	80005043.701244637,
				"jitter_ms":	0.16131707461331851,
				"lost_packets":	0,
				"packets":	7813,
				"lost_percent":	0,
				"omitted":	false,
				"sender":	false
			}
		}, {
			"streams":	[{
					"socket":	5,
					"start":	25.00006,
					"end":	26.000059,
					"seconds":	0.99999898672103882,
					"bytes":	9999360,
					"bits_per_second":	79994961.057211041,
					"jitter_ms":	0.168077974347174,
					"lost_packets":	0,
					"packets":	7812,
					"lost_percent":	0,
					"omitted":	false,
					"sender":	false
				}],
			"sum":	{
				"start":	25.00006,
				"end":	26.000059,
				"seconds":	0.99999898672103882,
				"bytes":	9999360,
				"bits_per_second":	79994961.057211041,
				"jitter_ms":	0.168077974347174,
				"lost_packets":	0,
				"packets":	7812,
				"lost_percent":	0,
				"omitted":	false,
				"sender":	false
			}
		}, {
			"streams":	[{
					"socket":	5,
					"start":	26.000059,
					"end":	27.00006,
					"seconds":	1.0000009536743164,
					"bytes":	10000640,
					"bits_per_second":	80005043.701244637,
					"jitter_ms":	0.16039995408875346,
					"lost_packets":	0,
					"packets":	7813,
					"lost_percent":	0,
					"omitted":	false,
					"sender":	false
				}],
			"sum":	{
				"start":	26.000059,
				"end":	27.00006,
				"seconds":	1.0000009536743164,
				"bytes":	10000640,
				"bits_per_second":	80005043.701244637,
				"jitter_ms":	0.16039995408875346,
				"lost_packets":	0,
				"packets":	7813,
				"lost_percent":	0,
				"omitted":	false,
				"sender":	false
			}
		}, {
			"streams":	[{
					"socket":	5,
					"start":	27.00006,
					"end":	28.000079,
					"seconds":	1.0000189542770386,
					"bytes":	9999360,
					"bits_per_second":	79993363.7836216,
					"jitter_ms":	0.1550194090883826,
					"lost_packets":	0,
					"packets":	7812,
					"lost_percent":	0,
					"omitted":	false,
					"sender":	false
				}],
			"sum":	{
				"start":	27.00006,
				"end":	28.000079,
				"seconds":	1.0000189542770386,
				"bytes":	9999360,
				"bits_per_second":	79993363.7836216,
				"jitter_ms":	0.1550194090883826,
				"lost_packets":	0,
				"packets":	7812,
				"lost_percent":	0,
				"omitted":	false,
				"sender":	false
			}
		}, {
			"streams":	[{
					"socket":	5,
					"start":	28.000079,
					"end":	29.000059,
					"seconds":	0.99997997283935547,
					"bytes":	9999360,
					"bits_per_second":	79996482.102398068,
					"jitter_ms":	0.16130306971812552,
					"lost_packets":	0,
					"packets":	7813,
					"lost_percent":	0,
					"omitted":	false,
					"sender":	false
				}],
			"sum":	{
				"start":	28.000079,
				"end":	29.000059,
				"seconds":	0.99997997283935547,
				"bytes":	9999360,
				"bits_per_second":	79996482.102398068,
				"jitter_ms":	0.16130306971812552,
				"lost_packets":	0,
				"packets":	7813,
				"lost_percent":	0,
				"omitted":	false,
				"sender":	false
			}
		}, {
			"streams":	[{
					"socket":	5,
					"start":	29.000059,
					"end":	30.00006,
					"seconds":	1.0000009536743164,
					"bytes":	9999360,
					"bits_per_second":	79994803.711010247,
					"jitter_ms":	0.16786787494242292,
					"lost_packets":	0,
					"packets":	7812,
					"lost_percent":	0,
					"omitted":	false,
					"sender":	false
				}],
			"sum":	{
				"start":	29.000059,
				"end":	30.00006,
				"seconds":	1.0000009536743164,
				"bytes":	9999360,
				"bits_per_second":	79994803.711010247,
				"jitter_ms":	0.16786787494242292,
				"lost_packets":	0,
				"packets":	7812,
				"lost_percent":	0,
				"omitted":	false,
				"sender":	false
			}
		}, {
			"streams":	[{
					"socket":	5,
					"start":	30.00006,
					"end":	30.000858,
					"seconds":	0.0007980000227689743,
					"bytes":	7680,
					"bits_per_second":	76992479.006215826,
					"jitter_ms":	0.17115316255969909,
					"lost_packets":	0,
					"packets":	6,
					"lost_percent":	0,
					"omitted":	false,
					"sender":	false
				}],
			"sum":	{
				"start":	30.00006,
				"end":	30.000858,
				"seconds":	0.0007980000227689743,
				"bytes":	7680,
				"bits_per_second":	76992479.006215826,
				"jitter_ms":	0.17115316255969909,
				"lost_packets":	0,
				"packets":	6,
				"lost_percent":	0,
				"omitted":	false,
				"sender":	false
			}
		}],
	"end":	{
		"streams":	[{
				"udp":	{
					"socket":	5,
					"start":	0,
					"end":	30.000858,
					"seconds":	30.000858,
					"bytes":	0,
					"bits_per_second":	0,
					"jitter_ms":	0.17115316255969909,
					"lost_packets":	0,
					"packets":	234367,
					"lost_percent":	0,
					"out_of_order":	0,
					"sender":	false
				}
			}],
		"sum":	{
			"start":	0,
			"end":	30.000858,
			"seconds":	30.000858,
			"bytes":	0,
			"bits_per_second":	0,
			"jitter_ms":	0.17115316255969909,
			"lost_packets":	0,
			"packets":	234367,
			"lost_percent":	0,
			"sender":	false
		},
		"sum_sent":	{
			"start":	0,
			"end":	30.000858,
			"seconds":	30.000858,
			"bytes":	0,
			"bits_per_second":	0,
			"jitter_ms":	0,
			"lost_packets":	0,
			"packets":	0,
			"lost_percent":	0,
			"sender":	true
		},
		"sum_received":	{
			"start":	0,
			"end":	30.000858,
			"seconds":	30.000858,
			"bytes":	299989760,
			"bits_per_second":	79994981.4768631,
			"jitter_ms":	0.17115316255969909,
			"lost_packets":	0,
			"packets":	234367,
			"lost_percent":	0,
			"sender":	false
		},
		"cpu_utilization_percent":	{
			"host_total":	7.7985946206154635,
			"host_user":	2.2979235900082489,
			"host_system":	5.5006710306072151,
			"remote_total":	15.388693277920682,
			"remote_user":	7.6943416393426443,
			"remote_system":	7.6943416393426443
		}
 }
 }
