{
	"start":	{
		"connected":	[{
				"socket":	5,
				"local_host":	"192.168.0.140",
				"local_port":	5201,
				"remote_host":	"192.168.0.118",
				"remote_port":	50718
			}],
		"version":	"iperf 3.16",
		"system_info":	"Linux nixos 6.1.79 #1-NixOS SMP PREEMPT_DYNAMIC Fri Feb 23 08:12:53 UTC 2024 x86_64",
		"target_bitrate":	80000000,
		"timestamp":	{
			"time":	"Sat, 20 Apr 2024 00:25:59 GMT",
			"timesecs":	1713572759
		},
		"accepted_connection":	{
			"host":	"192.168.0.118",
			"port":	36338
		},
		"cookie":	"qbdfxitywvluzdftjljrvucnmou37nlqzcc6",
		"target_bitrate":	80000000,
		"fq_rate":	0,
		"sock_bufsize":	0,
		"sndbuf_actual":	212992,
		"rcvbuf_actual":	212992,
		"test_start":	{
			"protocol":	"UDP",
			"num_streams":	1,
			"blksize":	128,
			"omit":	0,
			"duration":	30,
			"bytes":	0,
			"blocks":	0,
			"reverse":	0,
			"tos":	0,
			"target_bitrate":	80000000,
			"bidir":	0,
			"fqrate":	0
		}
	},
	"intervals":	[{
			"streams":	[{
					"socket":	5,
					"start":	0,
					"end":	1.000059,
					"seconds":	1.0000590085983276,
					"bytes":	2173696,
					"bits_per_second":	17388541.926513955,
					"jitter_ms":	0.074592379107658174,
					"lost_packets":	46509,
					"packets":	63491,
					"lost_percent":	73.25290198610827,
					"omitted":	false,
					"sender":	false
				}],
			"sum":	{
				"start":	0,
				"end":	1.000059,
				"seconds":	1.0000590085983276,
				"bytes":	2173696,
				"bits_per_second":	17388541.926513955,
				"jitter_ms":	0.074592379107658174,
				"lost_packets":	46509,
				"packets":	63491,
				"lost_percent":	73.25290198610827,
				"omitted":	false,
				"sender":	false
			}
		}, {
			"streams":	[{
					"socket":	5,
					"start":	1.000059,
					"end":	2.000018,
					"seconds":	0.99995899200439453,
					"bytes":	3442560,
					"bits_per_second":	27541609.426198319,
					"jitter_ms":	0.055267873522931325,
					"lost_packets":	37522,
					"packets":	64417,
					"lost_percent":	58.24859897232097,
					"omitted":	false,
					"sender":	false
				}],
			"sum":	{
				"start":	1.000059,
				"end":	2.000018,
				"seconds":	0.99995899200439453,
				"bytes":	3442560,
				"bits_per_second":	27541609.426198319,
				"jitter_ms":	0.055267873522931325,
				"lost_packets":	37522,
				"packets":	64417,
				"lost_percent":	58.24859897232097,
				"omitted":	false,
				"sender":	false
			}
		}, {
			"streams":	[{
					"socket":	5,
					"start":	2.000018,
					"end":	3.000049,
					"seconds":	1.0000309944152832,
					"bytes":	3451776,
					"bits_per_second":	27613352.1402964,
					"jitter_ms":	0.0479711647735727,
					"lost_packets":	36735,
					"packets":	63702,
					"lost_percent":	57.6669492323632,
					"omitted":	false,
					"sender":	false
				}],
			"sum":	{
				"start":	2.000018,
				"end":	3.000049,
				"seconds":	1.0000309944152832,
				"bytes":	3451776,
				"bits_per_second":	27613352.1402964,
				"jitter_ms":	0.0479711647735727,
				"lost_packets":	36735,
				"packets":	63702,
				"lost_percent":	57.6669492323632,
				"omitted":	false,
				"sender":	false
			}
		}, {
			"streams":	[{
					"socket":	5,
					"start":	3.000049,
					"end":	4.000058,
					"seconds":	1.0000089406967163,
					"bytes":	3450240,
					"bits_per_second":	27601673.221810862,
					"jitter_ms":	0.0851689082856479,
					"lost_packets":	37505,
					"packets":	64460,
					"lost_percent":	58.1833695314924,
					"omitted":	false,
					"sender":	false
				}],
			"sum":	{
				"start":	3.000049,
				"end":	4.000058,
				"seconds":	1.0000089406967163,
				"bytes":	3450240,
				"bits_per_second":	27601673.221810862,
				"jitter_ms":	0.0851689082856479,
				"lost_packets":	37505,
				"packets":	64460,
				"lost_percent":	58.1833695314924,
				"omitted":	false,
				"sender":	false
			}
		}, {
			"streams":	[{
					"socket":	5,
					"start":	4.000058,
					"end":	5.000058,
					"seconds":	1,
					"bytes":	3305088,
					"bits_per_second":	26440704,
					"jitter_ms":	0.085687745529674827,
					"lost_packets":	37333,
					"packets":	63154,
					"lost_percent":	59.1142287107705,
					"omitted":	false,
					"sender":	false
				}],
			"sum":	{
				"start":	4.000058,
				"end":	5.000058,
				"seconds":	1,
				"bytes":	3305088,
				"bits_per_second":	26440704,
				"jitter_ms":	0.085687745529674827,
				"lost_packets":	37333,
				"packets":	63154,
				"lost_percent":	59.1142287107705,
				"omitted":	false,
				"sender":	false
			}
		}, {
			"streams":	[{
					"socket":	5,
					"start":	5.000058,
					"end":	6.000059,
					"seconds":	1.0000009536743164,
					"bytes":	1732224,
					"bits_per_second":	13857778.78419229,
					"jitter_ms":	0.045734483539826877,
					"lost_packets":	52063,
					"packets":	65596,
					"lost_percent":	79.369168851759255,
					"omitted":	false,
					"sender":	false
				}],
			"sum":	{
				"start":	5.000058,
				"end":	6.000059,
				"seconds":	1.0000009536743164,
				"bytes":	1732224,
				"bits_per_second":	13857778.78419229,
				"jitter_ms":	0.045734483539826877,
				"lost_packets":	52063,
				"packets":	65596,
				"lost_percent":	79.369168851759255,
				"omitted":	false,
				"sender":	false
			}
		}, {
			"streams":	[{
					"socket":	5,
					"start":	6.000059,
					"end":	7.00006,
					"seconds":	1.0000009536743164,
					"bytes":	3457536,
					"bits_per_second":	27660261.621118907,
					"jitter_ms":	0.067226064561969959,
					"lost_packets":	37515,
					"packets":	64527,
					"lost_percent":	58.1384536705565,
					"omitted":	false,
					"sender":	false
				}],
			"sum":	{
				"start":	6.000059,
				"end":	7.00006,
				"seconds":	1.0000009536743164,
				"bytes":	3457536,
				"bits_per_second":	27660261.621118907,
				"jitter_ms":	0.067226064561969959,
				"lost_packets":	37515,
				"packets":	64527,
				"lost_percent":	58.1384536705565,
				"omitted":	false,
				"sender":	false
			}
		}, {
			"streams":	[{
					"socket":	5,
					"start":	7.00006,
					"end":	8.000091,
					"seconds":	1.0000309944152832,
					"bytes":	2530816,
					"bits_per_second":	20245900.490152426,
					"jitter_ms":	0.04761895321572783,
					"lost_packets":	43899,
					"packets":	63671,
					"lost_percent":	68.946616198897459,
					"omitted":	false,
					"sender":	false
				}],
			"sum":	{
				"start":	7.00006,
				"end":	8.000091,
				"seconds":	1.0000309944152832,
				"bytes":	2530816,
				"bits_per_second":	20245900.490152426,
				"jitter_ms":	0.04761895321572783,
				"lost_packets":	43899,
				"packets":	63671,
				"lost_percent":	68.946616198897459,
				"omitted":	false,
				"sender":	false
			}
		}, {
			"streams":	[{
					"socket":	5,
					"start":	8.000091,
					"end":	9.000092,
					"seconds":	1.0000009536743164,
					"bytes":	2952832,
					"bits_per_second":	23622633.471701171,
					"jitter_ms":	0.0852806516546215,
					"lost_packets":	42085,
					"packets":	65154,
					"lost_percent":	64.5931178438776,
					"omitted":	false,
					"sender":	false
				}],
			"sum":	{
				"start":	8.000091,
				"end":	9.000092,
				"seconds":	1.0000009536743164,
				"bytes":	2952832,
				"bits_per_second":	23622633.471701171,
				"jitter_ms":	0.0852806516546215,
				"lost_packets":	42085,
				"packets":	65154,
				"lost_percent":	64.5931178438776,
				"omitted":	false,
				"sender":	false
			}
		}, {
			"streams":	[{
					"socket":	5,
					"start":	9.000092,
					"end":	10.000095,
					"seconds":	1.0000029802322388,
					"bytes":	1687424,
					"bits_per_second":	13499351.768796656,
					"jitter_ms":	0.23456907153336742,
					"lost_packets":	49748,
					"packets":	62931,
					"lost_percent":	79.0516597543341,
					"omitted":	false,
					"sender":	false
				}],
			"sum":	{
				"start":	9.000092,
				"end":	10.000095,
				"seconds":	1.0000029802322388,
				"bytes":	1687424,
				"bits_per_second":	13499351.768796656,
				"jitter_ms":	0.23456907153336742,
				"lost_packets":	49748,
				"packets":	62931,
				"lost_percent":	79.0516597543341,
				"omitted":	false,
				"sender":	false
			}
		}, {
			"streams":	[{
					"socket":	5,
					"start":	10.000095,
					"end":	11.000059,
					"seconds":	0.99996399879455566,
					"bytes":	2535168,
					"bits_per_second":	20282074.17911936,
					"jitter_ms":	0.049744386481348275,
					"lost_packets":	46165,
					"packets":	65971,
					"lost_percent":	69.977717481923875,
					"omitted":	false,
					"sender":	false
				}],
			"sum":	{
				"start":	10.000095,
				"end":	11.000059,
				"seconds":	0.99996399879455566,
				"bytes":	2535168,
				"bits_per_second":	20282074.17911936,
				"jitter_ms":	0.049744386481348275,
				"lost_packets":	46165,
				"packets":	65971,
				"lost_percent":	69.977717481923875,
				"omitted":	false,
				"sender":	false
			}
		}, {
			"streams":	[{
					"socket":	5,
					"start":	11.000059,
					"end":	12.00009,
					"seconds":	1.0000309944152832,
					"bytes":	3448704,
					"bits_per_second":	27588776.901991542,
					"jitter_ms":	0.0658780079411073,
					"lost_packets":	37447,
					"packets":	64390,
					"lost_percent":	58.1565460475229,
					"omitted":	false,
					"sender":	false
				}],
			"sum":	{
				"start":	11.000059,
				"end":	12.00009,
				"seconds":	1.0000309944152832,
				"bytes":	3448704,
				"bits_per_second":	27588776.901991542,
				"jitter_ms":	0.0658780079411073,
				"lost_packets":	37447,
				"packets":	64390,
				"lost_percent":	58.1565460475229,
				"omitted":	false,
				"sender":	false
			}
		}, {
			"streams":	[{
					"socket":	5,
					"start":	12.00009,
					"end":	13.000021,
					"seconds":	0.99993097782135,
					"bytes":	3442688,
					"bits_per_second":	27543405.105827842,
					"jitter_ms":	0.050814209606072157,
					"lost_packets":	37430,
					"packets":	64326,
					"lost_percent":	58.1879799769922,
					"omitted":	false,
					"sender":	false
				}],
			"sum":	{
				"start":	12.00009,
				"end":	13.000021,
				"seconds":	0.99993097782135,
				"bytes":	3442688,
				"bits_per_second":	27543405.105827842,
				"jitter_ms":	0.050814209606072157,
				"lost_packets":	37430,
				"packets":	64326,
				"lost_percent":	58.1879799769922,
				"omitted":	false,
				"sender":	false
			}
		}, {
			"streams":	[{
					"socket":	5,
					"start":	13.000021,
					"end":	14.000058,
					"seconds":	1.0000369548797607,
					"bytes":	3449984,
					"bits_per_second":	27598852.087739564,
					"jitter_ms":	0.0681458458410876,
					"lost_packets":	37624,
					"packets":	64577,
					"lost_percent":	58.262229586385246,
					"omitted":	false,
					"sender":	false
				}],
			"sum":	{
				"start":	13.000021,
				"end":	14.000058,
				"seconds":	1.0000369548797607,
				"bytes":	3449984,
				"bits_per_second":	27598852.087739564,
				"jitter_ms":	0.0681458458410876,
				"lost_packets":	37624,
				"packets":	64577,
				"lost_percent":	58.262229586385246,
				"omitted":	false,
				"sender":	false
			}
		}, {
			"streams":	[{
					"socket":	5,
					"start":	14.000058,
					"end":	15.0001,
					"seconds":	1.0000419616699219,
					"bytes":	3300992,
					"bits_per_second":	26406827.92540291,
					"jitter_ms":	0.065283421861084934,
					"lost_packets":	37868,
					"packets":	63657,
					"lost_percent":	59.487566174968975,
					"omitted":	false,
					"sender":	false
				}],
			"sum":	{
				"start":	14.000058,
				"end":	15.0001,
				"seconds":	1.0000419616699219,
				"bytes":	3300992,
				"bits_per_second":	26406827.92540291,
				"jitter_ms":	0.065283421861084934,
				"lost_packets":	37868,
				"packets":	63657,
				"lost_percent":	59.487566174968975,
				"omitted":	false,
				"sender":	false
			}
		}, {
			"streams":	[{
					"socket":	5,
					"start":	15.0001,
					"end":	16.000091,
					"seconds":	0.999990999698639,
					"bytes":	1720192,
					"bits_per_second":	13761659.85908596,
					"jitter_ms":	0.063472708399738578,
					"lost_packets":	51102,
					"packets":	64541,
					"lost_percent":	79.1775770440495,
					"omitted":	false,
					"sender":	false
				}],
			"sum":	{
				"start":	15.0001,
				"end":	16.000091,
				"seconds":	0.999990999698639,
				"bytes":	1720192,
				"bits_per_second":	13761659.85908596,
				"jitter_ms":	0.063472708399738578,
				"lost_packets":	51102,
				"packets":	64541,
				"lost_percent":	79.1775770440495,
				"omitted":	false,
				"sender":	false
			}
		}, {
			"streams":	[{
					"socket":	5,
					"start":	16.000091,
					"end":	17.00006,
					"seconds":	0.9999690055847168,
					"bytes":	3444480,
					"bits_per_second":	27556694.103620879,
					"jitter_ms":	0.0699051559347475,
					"lost_packets":	38072,
					"packets":	64982,
					"lost_percent":	58.5885322089194,
					"omitted":	false,
					"sender":	false
				}],
			"sum":	{
				"start":	16.000091,
				"end":	17.00006,
				"seconds":	0.9999690055847168,
				"bytes":	3444480,
				"bits_per_second":	27556694.103620879,
				"jitter_ms":	0.0699051559347475,
				"lost_packets":	38072,
				"packets":	64982,
				"lost_percent":	58.5885322089194,
				"omitted":	false,
				"sender":	false
			}
		}, {
			"streams":	[{
					"socket":	5,
					"start":	17.00006,
					"end":	18.000063,
					"seconds":	1.0000029802322388,
					"bytes":	3442176,
					"bits_per_second":	27537325.932373486,
					"jitter_ms":	0.04326928696650495,
					"lost_packets":	37644,
					"packets":	64536,
					"lost_percent":	58.330234287839346,
					"omitted":	false,
					"sender":	false
				}],
			"sum":	{
				"start":	17.00006,
				"end":	18.000063,
				"seconds":	1.0000029802322388,
				"bytes":	3442176,
				"bits_per_second":	27537325.932373486,
				"jitter_ms":	0.04326928696650495,
				"lost_packets":	37644,
				"packets":	64536,
				"lost_percent":	58.330234287839346,
				"omitted":	false,
				"sender":	false
			}
		}, {
			"streams":	[{
					"socket":	5,
					"start":	18.000063,
					"end":	19.000059,
					"seconds":	0.9999960064888,
					"bytes":	3451520,
					"bits_per_second":	27612270.269910578,
					"jitter_ms":	0.053233035497431816,
					"lost_packets":	37486,
					"packets":	64451,
					"lost_percent":	58.162014553691954,
					"omitted":	false,
					"sender":	false
				}],
			"sum":	{
				"start":	18.000063,
				"end":	19.000059,
				"seconds":	0.9999960064888,
				"bytes":	3451520,
				"bits_per_second":	27612270.269910578,
				"jitter_ms":	0.053233035497431816,
				"lost_packets":	37486,
				"packets":	64451,
				"lost_percent":	58.162014553691954,
				"omitted":	false,
				"sender":	false
			}
		}, {
			"streams":	[{
					"socket":	5,
					"start":	19.000059,
					"end":	20.000092,
					"seconds":	1.0000330209732056,
					"bytes":	3234176,
					"bits_per_second":	25872553.66309873,
					"jitter_ms":	0.049859756215700726,
					"lost_packets":	38198,
					"packets":	63465,
					"lost_percent":	60.187504923973847,
					"omitted":	false,
					"sender":	false
				}],
			"sum":	{
				"start":	19.000059,
				"end":	20.000092,
				"seconds":	1.0000330209732056,
				"bytes":	3234176,
				"bits_per_second":	25872553.66309873,
				"jitter_ms":	0.049859756215700726,
				"lost_packets":	38198,
				"packets":	63465,
				"lost_percent":	60.187504923973847,
				"omitted":	false,
				"sender":	false
			}
		}, {
			"streams":	[{
					"socket":	5,
					"start":	20.000092,
					"end":	21.000143,
					"seconds":	1.0000510215759277,
					"bytes":	1683456,
					"bits_per_second":	13466960.894432209,
					"jitter_ms":	0.0679966726428305,
					"lost_packets":	50677,
					"packets":	63829,
					"lost_percent":	79.3949458709991,
					"omitted":	false,
					"sender":	false
				}],
			"sum":	{
				"start":	20.000092,
				"end":	21.000143,
				"seconds":	1.0000510215759277,
				"bytes":	1683456,
				"bits_per_second":	13466960.894432209,
				"jitter_ms":	0.0679966726428305,
				"lost_packets":	50677,
				"packets":	63829,
				"lost_percent":	79.3949458709991,
				"omitted":	false,
				"sender":	false
			}
		}, {
			"streams":	[{
					"socket":	5,
					"start":	21.000143,
					"end":	22.000088,
					"seconds":	0.99994498491287231,
					"bytes":	2789376,
					"bits_per_second":	22316235.729653031,
					"jitter_ms":	0.067154644756216936,
					"lost_packets":	44020,
					"packets":	65812,
					"lost_percent":	66.8874977207804,
					"omitted":	false,
					"sender":	false
				}],
			"sum":	{
				"start":	21.000143,
				"end":	22.000088,
				"seconds":	0.99994498491287231,
				"bytes":	2789376,
				"bits_per_second":	22316235.729653031,
				"jitter_ms":	0.067154644756216936,
				"lost_packets":	44020,
				"packets":	65812,
				"lost_percent":	66.8874977207804,
				"omitted":	false,
				"sender":	false
			}
		}, {
			"streams":	[{
					"socket":	5,
					"start":	22.000088,
					"end":	23.00006,
					"seconds":	0.99997198581695557,
					"bytes":	3347328,
					"bits_per_second":	26779374.202290718,
					"jitter_ms":	0.0632222103990085,
					"lost_packets":	37063,
					"packets":	63214,
					"lost_percent":	58.630999462144459,
					"omitted":	false,
					"sender":	false
				}],
			"sum":	{
				"start":	22.000088,
				"end":	23.00006,
				"seconds":	0.99997198581695557,
				"bytes":	3347328,
				"bits_per_second":	26779374.202290718,
				"jitter_ms":	0.0632222103990085,
				"lost_packets":	37063,
				"packets":	63214,
				"lost_percent":	58.630999462144459,
				"omitted":	false,
				"sender":	false
			}
		}, {
			"streams":	[{
					"socket":	5,
					"start":	23.00006,
					"end":	24.000093,
					"seconds":	1.0000330209732056,
					"bytes":	2149248,
					"bits_per_second":	17193416.256662477,
					"jitter_ms":	0.059418915811487533,
					"lost_packets":	48849,
					"packets":	65640,
					"lost_percent":	74.419561243144429,
					"omitted":	false,
					"sender":	false
				}],
			"sum":	{
				"start":	23.00006,
				"end":	24.000093,
				"seconds":	1.0000330209732056,
				"bytes":	2149248,
				"bits_per_second":	17193416.256662477,
				"jitter_ms":	0.059418915811487533,
				"lost_packets":	48849,
				"packets":	65640,
				"lost_percent":	74.419561243144429,
				"omitted":	false,
				"sender":	false
			}
		}, {
			"streams":	[{
					"socket":	5,
					"start":	24.000093,
					"end":	25.000091,
					"seconds":	0.99999797344207764,
					"bytes":	2502016,
					"bits_per_second":	20016168.563924979,
					"jitter_ms":	0.045224284989196666,
					"lost_packets":	44773,
					"packets":	64320,
					"lost_percent":	69.609763681592042,
					"omitted":	false,
					"sender":	false
				}],
			"sum":	{
				"start":	24.000093,
				"end":	25.000091,
				"seconds":	0.99999797344207764,
				"bytes":	2502016,
				"bits_per_second":	20016168.563924979,
				"jitter_ms":	0.045224284989196666,
				"lost_packets":	44773,
				"packets":	64320,
				"lost_percent":	69.609763681592042,
				"omitted":	false,
				"sender":	false
			}
		}, {
			"streams":	[{
					"socket":	5,
					"start":	25.000091,
					"end":	26.000059,
					"seconds":	0.99996799230575562,
					"bytes":	2514048,
					"bits_per_second":	20113027.771643244,
					"jitter_ms":	0.075422777987543835,
					"lost_packets":	44830,
					"packets":	64471,
					"lost_percent":	69.5351398303113,
					"omitted":	false,
					"sender":	false
				}],
			"sum":	{
				"start":	25.000091,
				"end":	26.000059,
				"seconds":	0.99996799230575562,
				"bytes":	2514048,
				"bits_per_second":	20113027.771643244,
				"jitter_ms":	0.075422777987543835,
				"lost_packets":	44830,
				"packets":	64471,
				"lost_percent":	69.5351398303113,
				"omitted":	false,
				"sender":	false
			}
		}, {
			"streams":	[{
					"socket":	5,
					"start":	26.000059,
					"end":	27.000005,
					"seconds":	0.9999459981918335,
					"bytes":	3448704,
					"bits_per_second":	27591121.970475748,
					"jitter_ms":	0.092918126630922734,
					"lost_packets":	37602,
					"packets":	64546,
					"lost_percent":	58.256127413007775,
					"omitted":	false,
					"sender":	false
				}],
			"sum":	{
				"start":	26.000059,
				"end":	27.000005,
				"seconds":	0.9999459981918335,
				"bytes":	3448704,
				"bits_per_second":	27591121.970475748,
				"jitter_ms":	0.092918126630922734,
				"lost_packets":	37602,
				"packets":	64546,
				"lost_percent":	58.256127413007775,
				"omitted":	false,
				"sender":	false
			}
		}, {
			"streams":	[{
					"socket":	5,
					"start":	27.000005,
					"end":	28.000006,
					"seconds":	1.0000009536743164,
					"bytes":	3447040,
					"bits_per_second":	27576293.701196954,
					"jitter_ms":	0.078544049166139038,
					"lost_packets":	37492,
					"packets":	64422,
					"lost_percent":	58.197510167334137,
					"omitted":	false,
					"sender":	false
				}],
			"sum":	{
				"start":	27.000005,
				"end":	28.000006,
				"seconds":	1.0000009536743164,
				"bytes":	3447040,
				"bits_per_second":	27576293.701196954,
				"jitter_ms":	0.078544049166139038,
				"lost_packets":	37492,
				"packets":	64422,
				"lost_percent":	58.197510167334137,
				"omitted":	false,
				"sender":	false
			}
		}, {
			"streams":	[{
					"socket":	5,
					"start":	28.000006,
					"end":	29.000059,
					"seconds":	1.00005304813385,
					"bytes":	3447040,
					"bits_per_second":	27574857.205284078,
					"jitter_ms":	0.0474547109360834,
					"lost_packets":	37478,
					"packets":	64408,
					"lost_percent":	58.188423798285925,
					"omitted":	false,
					"sender":	false
				}],
			"sum":	{
				"start":	28.000006,
				"end":	29.000059,
				"seconds":	1.00005304813385,
				"bytes":	3447040,
				"bits_per_second":	27574857.205284078,
				"jitter_ms":	0.0474547109360834,
				"lost_packets":	37478,
				"packets":	64408,
				"lost_percent":	58.188423798285925,
				"omitted":	false,
				"sender":	false
			}
		}, {
			"streams":	[{
					"socket":	5,
					"start":	29.000059,
					"end":	30.000094,
					"seconds":	1.0000350475311279,
					"bytes":	2442624,
					"bits_per_second":	19540307.160476543,
					"jitter_ms":	0.067504622258230174,
					"lost_packets":	44059,
					"packets":	63142,
					"lost_percent":	69.777644040416831,
					"omitted":	false,
					"sender":	false
				}],
			"sum":	{
				"start":	29.000059,
				"end":	30.000094,
				"seconds":	1.0000350475311279,
				"bytes":	2442624,
				"bits_per_second":	19540307.160476543,
				"jitter_ms":	0.067504622258230174,
				"lost_packets":	44059,
				"packets":	63142,
				"lost_percent":	69.777644040416831,
				"omitted":	false,
				"sender":	false
			}
		}, {
			"streams":	[{
					"socket":	5,
					"start":	30.000094,
					"end":	30.205283,
					"seconds":	0.20518900454044342,
					"bytes":	48256,
					"bits_per_second":	1881426.350620599,
					"jitter_ms":	0.048262793392162322,
					"lost_packets":	1649,
					"packets":	2026,
					"lost_percent":	81.3919052319842,
					"omitted":	false,
					"sender":	false
				}],
			"sum":	{
				"start":	30.000094,
				"end":	30.205283,
				"seconds":	0.20518900454044342,
				"bytes":	48256,
				"bits_per_second":	1881426.350620599,
				"jitter_ms":	0.048262793392162322,
				"lost_packets":	1649,
				"packets":	2026,
				"lost_percent":	81.3919052319842,
				"omitted":	false,
				"sender":	false
			}
		}],
	"end":	{
		"streams":	[{
				"udp":	{
					"socket":	5,
					"start":	0,
					"end":	30.205283,
					"seconds":	30.205283,
					"bytes":	0,
					"bits_per_second":	0,
					"jitter_ms":	0.048262793392162322,
					"lost_packets":	1248442,
					"packets":	1931829,
					"lost_percent":	0,
					"out_of_order":	0,
					"sender":	false
				}
			}],
		"sum":	{
			"start":	0,
			"end":	30.205283,
			"seconds":	30.205283,
			"bytes":	0,
			"bits_per_second":	0,
			"jitter_ms":	0.048262793392162322,
			"lost_packets":	1248442,
			"packets":	1931829,
			"lost_percent":	64.624871041898629,
			"sender":	false
		},
		"sum_sent":	{
			"start":	0,
			"end":	30.205283,
			"seconds":	30.205283,
			"bytes":	0,
			"bits_per_second":	0,
			"jitter_ms":	0,
			"lost_packets":	0,
			"packets":	0,
			"lost_percent":	0,
			"sender":	true
		},
		"sum_received":	{
			"start":	0,
			"end":	30.205283,
			"seconds":	30.205283,
			"bytes":	87473536,
			"bits_per_second":	23167744.794842675,
			"jitter_ms":	0.048262793392162322,
			"lost_packets":	1248442,
			"packets":	1931829,
			"lost_percent":	64.624871041898629,
			"sender":	false
		},
		"cpu_utilization_percent":	{
			"host_total":	22.081596027504318,
			"host_user":	6.2181616242503717,
			"host_system":	15.863434403253946,
			"remote_total":	54.989308541228,
			"remote_user":	7.2586995717083669,
			"remote_system":	47.73060563645894
		}
 }
 }
