{
	"start":	{
		"connected":	[{
				"socket":	5,
				"local_host":	"192.168.0.140",
				"local_port":	5201,
				"remote_host":	"192.168.0.118",
				"remote_port":	56522
			}],
		"version":	"iperf 3.16",
		"system_info":	"Linux nixos 6.1.79 #1-NixOS SMP PREEMPT_DYNAMIC Fri Feb 23 08:12:53 UTC 2024 x86_64",
		"target_bitrate":	80000000,
		"timestamp":	{
			"time":	"Sat, 20 Apr 2024 00:51:02 GMT",
			"timesecs":	1713574262
		},
		"accepted_connection":	{
			"host":	"192.168.0.118",
			"port":	33258
		},
		"cookie":	"tcgq6dzuy7r53uq26uhhmdlpx6ny4htse6mu",
		"target_bitrate":	80000000,
		"fq_rate":	0,
		"sock_bufsize":	0,
		"sndbuf_actual":	212992,
		"rcvbuf_actual":	212992,
		"test_start":	{
			"protocol":	"UDP",
			"num_streams":	1,
			"blksize":	512,
			"omit":	0,
			"duration":	30,
			"bytes":	0,
			"blocks":	0,
			"reverse":	0,
			"tos":	0,
			"target_bitrate":	80000000,
			"bidir":	0,
			"fqrate":	0
		}
	},
	"intervals":	[{
			"streams":	[{
					"socket":	5,
					"start":	0,
					"end":	1.000059,
					"seconds":	1.0000590085983276,
					"bytes":	8338944,
					"bits_per_second":	66707615.677101113,
					"jitter_ms":	0.11618996170296232,
					"lost_packets":	3212,
					"packets":	19499,
					"lost_percent":	16.472639622544747,
					"omitted":	false,
					"sender":	false
				}],
			"sum":	{
				"start":	0,
				"end":	1.000059,
				"seconds":	1.0000590085983276,
				"bytes":	8338944,
				"bits_per_second":	66707615.677101113,
				"jitter_ms":	0.11618996170296232,
				"lost_packets":	3212,
				"packets":	19499,
				"lost_percent":	16.472639622544747,
				"omitted":	false,
				"sender":	false
			}
		}, {
			"streams":	[{
					"socket":	5,
					"start":	1.000059,
					"end":	2.000056,
					"seconds":	0.99999701976776123,
					"bytes":	10000896,
					"bits_per_second":	80007406.440652,
					"jitter_ms":	0.11508358901221845,
					"lost_packets":	0,
					"packets":	19533,
					"lost_percent":	0,
					"omitted":	false,
					"sender":	false
				}],
			"sum":	{
				"start":	1.000059,
				"end":	2.000056,
				"seconds":	0.99999701976776123,
				"bytes":	10000896,
				"bits_per_second":	80007406.440652,
				"jitter_ms":	0.11508358901221845,
				"lost_packets":	0,
				"packets":	19533,
				"lost_percent":	0,
				"omitted":	false,
				"sender":	false
			}
		}, {
			"streams":	[{
					"socket":	5,
					"start":	2.000056,
					"end":	3.000109,
					"seconds":	1.00005304813385,
					"bytes":	9831424,
					"bits_per_second":	78647219.9117512,
					"jitter_ms":	0.077906238424967855,
					"lost_packets":	0,
					"packets":	19203,
					"lost_percent":	0,
					"omitted":	false,
					"sender":	false
				}],
			"sum":	{
				"start":	2.000056,
				"end":	3.000109,
				"seconds":	1.00005304813385,
				"bytes":	9831424,
				"bits_per_second":	78647219.9117512,
				"jitter_ms":	0.077906238424967855,
				"lost_packets":	0,
				"packets":	19203,
				"lost_percent":	0,
				"omitted":	false,
				"sender":	false
			}
		}, {
			"streams":	[{
					"socket":	5,
					"start":	3.000109,
					"end":	4.00001,
					"seconds":	0.999900996685028,
					"bytes":	3370496,
					"bits_per_second":	26966637.786534514,
					"jitter_ms":	0.09980658308364064,
					"lost_packets":	12506,
					"packets":	19089,
					"lost_percent":	65.5141704646655,
					"omitted":	false,
					"sender":	false
				}],
			"sum":	{
				"start":	3.000109,
				"end":	4.00001,
				"seconds":	0.999900996685028,
				"bytes":	3370496,
				"bits_per_second":	26966637.786534514,
				"jitter_ms":	0.09980658308364064,
				"lost_packets":	12506,
				"packets":	19089,
				"lost_percent":	65.5141704646655,
				"omitted":	false,
				"sender":	false
			}
		}, {
			"streams":	[{
					"socket":	5,
					"start":	4.00001,
					"end":	5.000079,
					"seconds":	1.00006902217865,
					"bytes":	3674624,
					"bits_per_second":	29394963.095605809,
					"jitter_ms":	0.065014235383478322,
					"lost_packets":	12625,
					"packets":	19802,
					"lost_percent":	63.756186243813758,
					"omitted":	false,
					"sender":	false
				}],
			"sum":	{
				"start":	4.00001,
				"end":	5.000079,
				"seconds":	1.00006902217865,
				"bytes":	3674624,
				"bits_per_second":	29394963.095605809,
				"jitter_ms":	0.065014235383478322,
				"lost_packets":	12625,
				"packets":	19802,
				"lost_percent":	63.756186243813758,
				"omitted":	false,
				"sender":	false
			}
		}, {
			"streams":	[{
					"socket":	5,
					"start":	5.000079,
					"end":	6.000018,
					"seconds":	0.99993902444839478,
					"bytes":	8556544,
					"bits_per_second":	68456526.174444467,
					"jitter_ms":	0.087429218779626,
					"lost_packets":	3288,
					"packets":	20000,
					"lost_percent":	16.44,
					"omitted":	false,
					"sender":	false
				}],
			"sum":	{
				"start":	5.000079,
				"end":	6.000018,
				"seconds":	0.99993902444839478,
				"bytes":	8556544,
				"bits_per_second":	68456526.174444467,
				"jitter_ms":	0.087429218779626,
				"lost_packets":	3288,
				"packets":	20000,
				"lost_percent":	16.44,
				"omitted":	false,
				"sender":	false
			}
		}, {
			"streams":	[{
					"socket":	5,
					"start":	6.000018,
					"end":	7.000064,
					"seconds":	1.0000460147857666,
					"bytes":	10010112,
					"bits_per_second":	80077211.2642789,
					"jitter_ms":	0.0641593651167617,
					"lost_packets":	0,
					"packets":	19552,
					"lost_percent":	0,
					"omitted":	false,
					"sender":	false
				}],
			"sum":	{
				"start":	6.000018,
				"end":	7.000064,
				"seconds":	1.0000460147857666,
				"bytes":	10010112,
				"bits_per_second":	80077211.2642789,
				"jitter_ms":	0.0641593651167617,
				"lost_packets":	0,
				"packets":	19552,
				"lost_percent":	0,
				"omitted":	false,
				"sender":	false
			}
		}, {
			"streams":	[{
					"socket":	5,
					"start":	7.000064,
					"end":	8.00006,
					"seconds":	0.9999960064888,
					"bytes":	10006016,
					"bits_per_second":	80048447.67437233,
					"jitter_ms":	0.101717262162571,
					"lost_packets":	0,
					"packets":	19543,
					"lost_percent":	0,
					"omitted":	false,
					"sender":	false
				}],
			"sum":	{
				"start":	7.000064,
				"end":	8.00006,
				"seconds":	0.9999960064888,
				"bytes":	10006016,
				"bits_per_second":	80048447.67437233,
				"jitter_ms":	0.101717262162571,
				"lost_packets":	0,
				"packets":	19543,
				"lost_percent":	0,
				"omitted":	false,
				"sender":	false
			}
		}, {
			"streams":	[{
					"socket":	5,
					"start":	8.00006,
					"end":	9.000171,
					"seconds":	1.0001109838485718,
					"bytes":	7337472,
					"bits_per_second":	58693261.995898463,
					"jitter_ms":	0.10353184783893703,
					"lost_packets":	4440,
					"packets":	18771,
					"lost_percent":	23.653508070960523,
					"omitted":	false,
					"sender":	false
				}],
			"sum":	{
				"start":	8.00006,
				"end":	9.000171,
				"seconds":	1.0001109838485718,
				"bytes":	7337472,
				"bits_per_second":	58693261.995898463,
				"jitter_ms":	0.10353184783893703,
				"lost_packets":	4440,
				"packets":	18771,
				"lost_percent":	23.653508070960523,
				"omitted":	false,
				"sender":	false
			}
		}, {
			"streams":	[{
					"socket":	5,
					"start":	9.000171,
					"end":	10.000095,
					"seconds":	0.99992400407791138,
					"bytes":	3505664,
					"bits_per_second":	28047443.491330352,
					"jitter_ms":	0.2527383640141968,
					"lost_packets":	12362,
					"packets":	19209,
					"lost_percent":	64.355250143162053,
					"omitted":	false,
					"sender":	false
				}],
			"sum":	{
				"start":	9.000171,
				"end":	10.000095,
				"seconds":	0.99992400407791138,
				"bytes":	3505664,
				"bits_per_second":	28047443.491330352,
				"jitter_ms":	0.2527383640141968,
				"lost_packets":	12362,
				"packets":	19209,
				"lost_percent":	64.355250143162053,
				"omitted":	false,
				"sender":	false
			}
		}, {
			"streams":	[{
					"socket":	5,
					"start":	10.000095,
					"end":	11.00006,
					"seconds":	0.999965012073517,
					"bytes":	4710400,
					"bits_per_second":	37684518.503162943,
					"jitter_ms":	0.070185206681245449,
					"lost_packets":	10841,
					"packets":	20041,
					"lost_percent":	54.094107080485,
					"omitted":	false,
					"sender":	false
				}],
			"sum":	{
				"start":	10.000095,
				"end":	11.00006,
				"seconds":	0.999965012073517,
				"bytes":	4710400,
				"bits_per_second":	37684518.503162943,
				"jitter_ms":	0.070185206681245449,
				"lost_packets":	10841,
				"packets":	20041,
				"lost_percent":	54.094107080485,
				"omitted":	false,
				"sender":	false
			}
		}, {
			"streams":	[{
					"socket":	5,
					"start":	11.00006,
					"end":	12.000013,
					"seconds":	0.99995297193527222,
					"bytes":	10082816,
					"bits_per_second":	80666321.580992669,
					"jitter_ms":	0.061001775979145668,
					"lost_packets":	409,
					"packets":	20102,
					"lost_percent":	2.0346234205551688,
					"omitted":	false,
					"sender":	false
				}],
			"sum":	{
				"start":	11.00006,
				"end":	12.000013,
				"seconds":	0.99995297193527222,
				"bytes":	10082816,
				"bits_per_second":	80666321.580992669,
				"jitter_ms":	0.061001775979145668,
				"lost_packets":	409,
				"packets":	20102,
				"lost_percent":	2.0346234205551688,
				"omitted":	false,
				"sender":	false
			}
		}, {
			"streams":	[{
					"socket":	5,
					"start":	12.000013,
					"end":	13.000059,
					"seconds":	1.0000460147857666,
					"bytes":	10000896,
					"bits_per_second":	80003486.6567009,
					"jitter_ms":	0.10984938328667515,
					"lost_packets":	0,
					"packets":	19533,
					"lost_percent":	0,
					"omitted":	false,
					"sender":	false
				}],
			"sum":	{
				"start":	12.000013,
				"end":	13.000059,
				"seconds":	1.0000460147857666,
				"bytes":	10000896,
				"bits_per_second":	80003486.6567009,
				"jitter_ms":	0.10984938328667515,
				"lost_packets":	0,
				"packets":	19533,
				"lost_percent":	0,
				"omitted":	false,
				"sender":	false
			}
		}, {
			"streams":	[{
					"socket":	5,
					"start":	13.000059,
					"end":	14.000157,
					"seconds":	1.0000979900360107,
					"bytes":	7308800,
					"bits_per_second":	58464671.044778965,
					"jitter_ms":	0.0807142122487628,
					"lost_packets":	4105,
					"packets":	18380,
					"lost_percent":	22.33405875952122,
					"omitted":	false,
					"sender":	false
				}],
			"sum":	{
				"start":	13.000059,
				"end":	14.000157,
				"seconds":	1.0000979900360107,
				"bytes":	7308800,
				"bits_per_second":	58464671.044778965,
				"jitter_ms":	0.0807142122487628,
				"lost_packets":	4105,
				"packets":	18380,
				"lost_percent":	22.33405875952122,
				"omitted":	false,
				"sender":	false
			}
		}, {
			"streams":	[{
					"socket":	5,
					"start":	14.000157,
					"end":	15.00016,
					"seconds":	1.0000029802322388,
					"bytes":	3488768,
					"bits_per_second":	27910060.821536954,
					"jitter_ms":	0.080952572673460135,
					"lost_packets":	12669,
					"packets":	19483,
					"lost_percent":	65.025920032849157,
					"omitted":	false,
					"sender":	false
				}],
			"sum":	{
				"start":	14.000157,
				"end":	15.00016,
				"seconds":	1.0000029802322388,
				"bytes":	3488768,
				"bits_per_second":	27910060.821536954,
				"jitter_ms":	0.080952572673460135,
				"lost_packets":	12669,
				"packets":	19483,
				"lost_percent":	65.025920032849157,
				"omitted":	false,
				"sender":	false
			}
		}, {
			"streams":	[{
					"socket":	5,
					"start":	15.00016,
					"end":	16.000059,
					"seconds":	0.99989902973175049,
					"bytes":	4795904,
					"bits_per_second":	38371106.340900272,
					"jitter_ms":	0.099626113967494337,
					"lost_packets":	10954,
					"packets":	20321,
					"lost_percent":	53.9048275183308,
					"omitted":	false,
					"sender":	false
				}],
			"sum":	{
				"start":	15.00016,
				"end":	16.000059,
				"seconds":	0.99989902973175049,
				"bytes":	4795904,
				"bits_per_second":	38371106.340900272,
				"jitter_ms":	0.099626113967494337,
				"lost_packets":	10954,
				"packets":	20321,
				"lost_percent":	53.9048275183308,
				"omitted":	false,
				"sender":	false
			}
		}, {
			"streams":	[{
					"socket":	5,
					"start":	16.000059,
					"end":	17.000077,
					"seconds":	1.0000180006027222,
					"bytes":	10030080,
					"bits_per_second":	80239195.6461164,
					"jitter_ms":	0.11186441740122913,
					"lost_packets":	349,
					"packets":	19939,
					"lost_percent":	1.7503385325241989,
					"omitted":	false,
					"sender":	false
				}],
			"sum":	{
				"start":	16.000059,
				"end":	17.000077,
				"seconds":	1.0000180006027222,
				"bytes":	10030080,
				"bits_per_second":	80239195.6461164,
				"jitter_ms":	0.11186441740122913,
				"lost_packets":	349,
				"packets":	19939,
				"lost_percent":	1.7503385325241989,
				"omitted":	false,
				"sender":	false
			}
		}, {
			"streams":	[{
					"socket":	5,
					"start":	17.000077,
					"end":	18.000059,
					"seconds":	0.99998199939727783,
					"bytes":	9999872,
					"bits_per_second":	80000416.055707023,
					"jitter_ms":	0.11119810971976558,
					"lost_packets":	0,
					"packets":	19531,
					"lost_percent":	0,
					"omitted":	false,
					"sender":	false
				}],
			"sum":	{
				"start":	17.000077,
				"end":	18.000059,
				"seconds":	0.99998199939727783,
				"bytes":	9999872,
				"bits_per_second":	80000416.055707023,
				"jitter_ms":	0.11119810971976558,
				"lost_packets":	0,
				"packets":	19531,
				"lost_percent":	0,
				"omitted":	false,
				"sender":	false
			}
		}, {
			"streams":	[{
					"socket":	5,
					"start":	18.000059,
					"end":	19.000093,
					"seconds":	1.000033974647522,
					"bytes":	7355392,
					"bits_per_second":	58841136.893114261,
					"jitter_ms":	0.10306264844053936,
					"lost_packets":	4405,
					"packets":	18771,
					"lost_percent":	23.467050237067816,
					"omitted":	false,
					"sender":	false
				}],
			"sum":	{
				"start":	18.000059,
				"end":	19.000093,
				"seconds":	1.000033974647522,
				"bytes":	7355392,
				"bits_per_second":	58841136.893114261,
				"jitter_ms":	0.10306264844053936,
				"lost_packets":	4405,
				"packets":	18771,
				"lost_percent":	23.467050237067816,
				"omitted":	false,
				"sender":	false
			}
		}, {
			"streams":	[{
					"socket":	5,
					"start":	19.000093,
					"end":	20.000164,
					"seconds":	1.0000710487365723,
					"bytes":	3485696,
					"bits_per_second":	27883586.9063792,
					"jitter_ms":	0.0681618614789997,
					"lost_packets":	12304,
					"packets":	19112,
					"lost_percent":	64.378401004604441,
					"omitted":	false,
					"sender":	false
				}],
			"sum":	{
				"start":	19.000093,
				"end":	20.000164,
				"seconds":	1.0000710487365723,
				"bytes":	3485696,
				"bits_per_second":	27883586.9063792,
				"jitter_ms":	0.0681618614789997,
				"lost_packets":	12304,
				"packets":	19112,
				"lost_percent":	64.378401004604441,
				"omitted":	false,
				"sender":	false
			}
		}, {
			"streams":	[{
					"socket":	5,
					"start":	20.000164,
					"end":	21.000077,
					"seconds":	0.999912977218628,
					"bytes":	4882944,
					"bits_per_second":	39066951.714797951,
					"jitter_ms":	0.082819237675529,
					"lost_packets":	10805,
					"packets":	20342,
					"lost_percent":	53.1167043555206,
					"omitted":	false,
					"sender":	false
				}],
			"sum":	{
				"start":	20.000164,
				"end":	21.000077,
				"seconds":	0.999912977218628,
				"bytes":	4882944,
				"bits_per_second":	39066951.714797951,
				"jitter_ms":	0.082819237675529,
				"lost_packets":	10805,
				"packets":	20342,
				"lost_percent":	53.1167043555206,
				"omitted":	false,
				"sender":	false
			}
		}, {
			"streams":	[{
					"socket":	5,
					"start":	21.000077,
					"end":	22.000059,
					"seconds":	0.99998199939727783,
					"bytes":	9981952,
					"bits_per_second":	79857053.475094169,
					"jitter_ms":	0.10487892592392926,
					"lost_packets":	407,
					"packets":	19903,
					"lost_percent":	2.0449178515801636,
					"omitted":	false,
					"sender":	false
				}],
			"sum":	{
				"start":	21.000077,
				"end":	22.000059,
				"seconds":	0.99998199939727783,
				"bytes":	9981952,
				"bits_per_second":	79857053.475094169,
				"jitter_ms":	0.10487892592392926,
				"lost_packets":	407,
				"packets":	19903,
				"lost_percent":	2.0449178515801636,
				"omitted":	false,
				"sender":	false
			}
		}, {
			"streams":	[{
					"socket":	5,
					"start":	22.000059,
					"end":	23.000064,
					"seconds":	1.0000050067901611,
					"bytes":	9998336,
					"bits_per_second":	79986287.5254426,
					"jitter_ms":	0.0616527904681601,
					"lost_packets":	0,
					"packets":	19528,
					"lost_percent":	0,
					"omitted":	false,
					"sender":	false
				}],
			"sum":	{
				"start":	22.000059,
				"end":	23.000064,
				"seconds":	1.0000050067901611,
				"bytes":	9998336,
				"bits_per_second":	79986287.5254426,
				"jitter_ms":	0.0616527904681601,
				"lost_packets":	0,
				"packets":	19528,
				"lost_percent":	0,
				"omitted":	false,
				"sender":	false
			}
		}, {
			"streams":	[{
					"socket":	5,
					"start":	23.000064,
					"end":	24.000157,
					"seconds":	1.0000929832458496,
					"bytes":	7321600,
					"bits_per_second":	58567354.217304051,
					"jitter_ms":	0.095575285214125255,
					"lost_packets":	4279,
					"packets":	18579,
					"lost_percent":	23.031379514505623,
					"omitted":	false,
					"sender":	false
				}],
			"sum":	{
				"start":	23.000064,
				"end":	24.000157,
				"seconds":	1.0000929832458496,
				"bytes":	7321600,
				"bits_per_second":	58567354.217304051,
				"jitter_ms":	0.095575285214125255,
				"lost_packets":	4279,
				"packets":	18579,
				"lost_percent":	23.031379514505623,
				"omitted":	false,
				"sender":	false
			}
		}, {
			"streams":	[{
					"socket":	5,
					"start":	24.000157,
					"end":	25.000079,
					"seconds":	0.999921977519989,
					"bytes":	3488768,
					"bits_per_second":	27912321.78856881,
					"jitter_ms":	0.45764852102964221,
					"lost_packets":	13045,
					"packets":	19859,
					"lost_percent":	65.688101112845558,
					"omitted":	false,
					"sender":	false
				}],
			"sum":	{
				"start":	24.000157,
				"end":	25.000079,
				"seconds":	0.999921977519989,
				"bytes":	3488768,
				"bits_per_second":	27912321.78856881,
				"jitter_ms":	0.45764852102964221,
				"lost_packets":	13045,
				"packets":	19859,
				"lost_percent":	65.688101112845558,
				"omitted":	false,
				"sender":	false
			}
		}, {
			"streams":	[{
					"socket":	5,
					"start":	25.000079,
					"end":	26.000092,
					"seconds":	1.000012993812561,
					"bytes":	4861440,
					"bits_per_second":	38891014.65744523,
					"jitter_ms":	0.062254042454366929,
					"lost_packets":	10291,
					"packets":	19786,
					"lost_percent":	52.011523299302539,
					"omitted":	false,
					"sender":	false
				}],
			"sum":	{
				"start":	25.000079,
				"end":	26.000092,
				"seconds":	1.000012993812561,
				"bytes":	4861440,
				"bits_per_second":	38891014.65744523,
				"jitter_ms":	0.062254042454366929,
				"lost_packets":	10291,
				"packets":	19786,
				"lost_percent":	52.011523299302539,
				"omitted":	false,
				"sender":	false
			}
		}, {
			"streams":	[{
					"socket":	5,
					"start":	26.000092,
					"end":	27.000061,
					"seconds":	0.9999690055847168,
					"bytes":	9970176,
					"bits_per_second":	79763880.2348286,
					"jitter_ms":	0.10647458237587468,
					"lost_packets":	430,
					"packets":	19903,
					"lost_percent":	2.1604783198512787,
					"omitted":	false,
					"sender":	false
				}],
			"sum":	{
				"start":	26.000092,
				"end":	27.000061,
				"seconds":	0.9999690055847168,
				"bytes":	9970176,
				"bits_per_second":	79763880.2348286,
				"jitter_ms":	0.10647458237587468,
				"lost_packets":	430,
				"packets":	19903,
				"lost_percent":	2.1604783198512787,
				"omitted":	false,
				"sender":	false
			}
		}, {
			"streams":	[{
					"socket":	5,
					"start":	27.000061,
					"end":	28.000034,
					"seconds":	0.99997299909591675,
					"bytes":	9982464,
					"bits_per_second":	79861868.342647031,
					"jitter_ms":	0.091510377872679974,
					"lost_packets":	0,
					"packets":	19497,
					"lost_percent":	0,
					"omitted":	false,
					"sender":	false
				}],
			"sum":	{
				"start":	27.000061,
				"end":	28.000034,
				"seconds":	0.99997299909591675,
				"bytes":	9982464,
				"bits_per_second":	79861868.342647031,
				"jitter_ms":	0.091510377872679974,
				"lost_packets":	0,
				"packets":	19497,
				"lost_percent":	0,
				"omitted":	false,
				"sender":	false
			}
		}, {
			"streams":	[{
					"socket":	5,
					"start":	28.000034,
					"end":	29.000059,
					"seconds":	1.0000250339508057,
					"bytes":	7229440,
					"bits_per_second":	57834072.184682034,
					"jitter_ms":	0.10826051214465568,
					"lost_packets":	4659,
					"packets":	18779,
					"lost_percent":	24.809627775706907,
					"omitted":	false,
					"sender":	false
				}],
			"sum":	{
				"start":	28.000034,
				"end":	29.000059,
				"seconds":	1.0000250339508057,
				"bytes":	7229440,
				"bits_per_second":	57834072.184682034,
				"jitter_ms":	0.10826051214465568,
				"lost_packets":	4659,
				"packets":	18779,
				"lost_percent":	24.809627775706907,
				"omitted":	false,
				"sender":	false
			}
		}, {
			"streams":	[{
					"socket":	5,
					"start":	29.000059,
					"end":	30.000092,
					"seconds":	1.0000330209732056,
					"bytes":	3319296,
					"bits_per_second":	26553491.1778793,
					"jitter_ms":	0.0769063619177148,
					"lost_packets":	13008,
					"packets":	19491,
					"lost_percent":	66.73849468985685,
					"omitted":	false,
					"sender":	false
				}],
			"sum":	{
				"start":	29.000059,
				"end":	30.000092,
				"seconds":	1.0000330209732056,
				"bytes":	3319296,
				"bits_per_second":	26553491.1778793,
				"jitter_ms":	0.0769063619177148,
				"lost_packets":	13008,
				"packets":	19491,
				"lost_percent":	66.73849468985685,
				"omitted":	false,
				"sender":	false
			}
		}, {
			"streams":	[{
					"socket":	5,
					"start":	30.000092,
					"end":	30.052758,
					"seconds":	0.05266600102186203,
					"bytes":	151552,
					"bits_per_second":	23020847.918502823,
					"jitter_ms":	0.11105504303309491,
					"lost_packets":	531,
					"packets":	827,
					"lost_percent":	64.2079806529625,
					"omitted":	false,
					"sender":	false
				}],
			"sum":	{
				"start":	30.000092,
				"end":	30.052758,
				"seconds":	0.05266600102186203,
				"bytes":	151552,
				"bits_per_second":	23020847.918502823,
				"jitter_ms":	0.11105504303309491,
				"lost_packets":	531,
				"packets":	827,
				"lost_percent":	64.2079806529625,
				"omitted":	false,
				"sender":	false
			}
		}],
	"end":	{
		"streams":	[{
				"udp":	{
					"socket":	5,
					"start":	0,
					"end":	30.052758,
					"seconds":	30.052758,
					"bytes":	0,
					"bits_per_second":	0,
					"jitter_ms":	0.11105504303309491,
					"lost_packets":	161924,
					"packets":	585908,
					"lost_percent":	0,
					"out_of_order":	0,
					"sender":	false
				}
			}],
		"sum":	{
			"start":	0,
			"end":	30.052758,
			"seconds":	30.052758,
			"bytes":	0,
			"bits_per_second":	0,
			"jitter_ms":	0.11105504303309491,
			"lost_packets":	161924,
			"packets":	585908,
			"lost_percent":	27.636420734995937,
			"sender":	false
		},
		"sum_sent":	{
			"start":	0,
			"end":	30.052758,
			"seconds":	30.052758,
			"bytes":	0,
			"bits_per_second":	0,
			"jitter_ms":	0,
			"lost_packets":	0,
			"packets":	0,
			"lost_percent":	0,
			"sender":	true
		},
		"sum_received":	{
			"start":	0,
			"end":	30.052758,
			"seconds":	30.052758,
			"bytes":	217079808,
			"bits_per_second":	57786325.767505266,
			"jitter_ms":	0.11105504303309491,
			"lost_packets":	161924,
			"packets":	585908,
			"lost_percent":	27.636420734995937,
			"sender":	false
		},
		"cpu_utilization_percent":	{
			"host_total":	15.940629900650427,
			"host_user":	4.365524230694068,
			"host_system":	11.575102342476173,
			"remote_total":	35.001765647646053,
			"remote_user":	3.2478084388125184,
			"remote_system":	31.75394387690228
		}
 }
 }
